.DS_Store
namada/__init__.py
namada/src/__init__.py
namada/src/namada.py
namada/src/workshop.py
namada/src/commands/__init__.py
namada/src/commands/client.py
namada/src/commands/ethereum_bridge_pool.py
namada/src/commands/ibc_transfer.py
namada/src/commands/init_proposal.py
namada/src/commands/ledger.py
namada/src/commands/node.py
namada/src/commands/relayer.py
namada/src/commands/reveal_pk.py
namada/src/commands/transfer.py
namada/src/commands/tx.py
namada/src/commands/update_account.py
namada/src/commands/vote_proposal.py
namada/src/commands/wallet.py
namada/src/commands/sub/__init__.py
namada/src/commands/sub/client/__init__.py
namada/src/commands/sub/node/__init__.py
namada/src/commands/sub/node/config.py
namada/src/commands/sub/node/ledger.py
namada/src/commands/sub/relayer/__init__.py
namada/src/commands/sub/relayer/ethereum_bridge_pool.py
namada/src/commands/sub/relayer/validator_set.py
namada/src/commands/sub/wallet/__init__.py
namada/test/__init__.py
namada-1.0.31.dist-info/LICENSE
namada-1.0.31.dist-info/METADATA
namada-1.0.31.dist-info/WHEEL
namada-1.0.31.dist-info/top_level.txt
namada-1.0.31.dist-info/RECORD
