Metadata-Version: 2.1
Name: namada
Version: 1.0.31
Summary: Python package for Namada
Home-page: https://github.com/qmine/namada
Author: qmine
Author-email: self.crypto@protonmail.com
License: MIT
Classifier: License :: OSI Approved :: MIT License
Classifier: Programming Language :: Python :: 3.10
Classifier: Operating System :: OS Independent
Requires-Python: >=3.10
License-File: LICENSE
Requires-Dist: requests
Provides-Extra: dev
Requires-Dist: twine >=4.0.2 ; extra == 'dev'
